phontext/__init__.py
phontext/corpus.py
phontext/io.py
phontext/word.py
phontext-0.0.2.dist-info/LICENSE
phontext-0.0.2.dist-info/METADATA
phontext-0.0.2.dist-info/WHEEL
phontext-0.0.2.dist-info/top_level.txt
phontext-0.0.2.dist-info/RECORD
