Metadata-Version: 2.1
Name: phontext
Version: 0.0.2
Summary: Tools for doing phonology analysis.
Home-page: https://github.com/rolandomunoz/phontext
Author: Rolando Muñoz Aramburú
Author-email: rolando.muar@gmail.com
Project-URL: Bug Tracker, https://github.com/rolandomunoz/phontext/issues
Project-URL: Documentation, https://github.com/rolandomunoz/phontext
Project-URL: Source, https://github.com/rolandomunoz/phontext
Keywords: Phonology,Analysis,Linguistics
Classifier: Topic :: Text Processing :: Linguistic
Classifier: Programming Language :: Python :: 3
Classifier: License :: OSI Approved :: GNU General Public License v3 (GPLv3)
Classifier: Operating System :: OS Independent
Classifier: Intended Audience :: Developers
Requires-Python: >=3.6
License-File: LICENSE
